odoo/addons/product_variant_configurator_website_sale/README.rst
odoo/addons/product_variant_configurator_website_sale/__init__.py
odoo/addons/product_variant_configurator_website_sale/__manifest__.py
odoo/addons/product_variant_configurator_website_sale/i18n/it.po
odoo/addons/product_variant_configurator_website_sale/i18n/product_variant_configurator_website_sale.pot
odoo/addons/product_variant_configurator_website_sale/models/__init__.py
odoo/addons/product_variant_configurator_website_sale/models/product.py
odoo/addons/product_variant_configurator_website_sale/readme/CONFIGURE.rst
odoo/addons/product_variant_configurator_website_sale/readme/CONTRIBUTORS.rst
odoo/addons/product_variant_configurator_website_sale/readme/DESCRIPTION.rst
odoo/addons/product_variant_configurator_website_sale/static/description/icon.png
odoo/addons/product_variant_configurator_website_sale/static/description/index.html
odoo13_addon_product_variant_configurator_website_sale-13.0.1.0.1.dev6.dist-info/METADATA
odoo13_addon_product_variant_configurator_website_sale-13.0.1.0.1.dev6.dist-info/WHEEL
odoo13_addon_product_variant_configurator_website_sale-13.0.1.0.1.dev6.dist-info/top_level.txt
odoo13_addon_product_variant_configurator_website_sale-13.0.1.0.1.dev6.dist-info/RECORD
